django_sites/__init__.py
django_sites/base.py
django_sites/exceptions.py
django_sites/middleware.py
django_sites/models.py
django_sites/tests.py
django_sites/utils.py
django_sites/templatetags/__init__.py
django_sites/templatetags/_sities_resolve.py
django_sites-0.11.dist-info/LICENSE
django_sites-0.11.dist-info/METADATA
django_sites-0.11.dist-info/WHEEL
django_sites-0.11.dist-info/top_level.txt
django_sites-0.11.dist-info/RECORD
